{
  "id": "user-guide/tasks",
  "title": "Tasks",
  "description": "A task is an instance of launching an Ansible playbook. You can create the task from Task Template by clicking the button Run/Build/Deploy for the required template.",
  "source": "@site/docs/user-guide/tasks.md",
  "sourceDirName": "user-guide",
  "slug": "/user-guide/tasks",
  "permalink": "/user-guide/tasks",
  "draft": false,
  "unlisted": false,
  "editUrl": "https://github.com/semaphoreui/semaphore-docs/edit/main/docs/user-guide/tasks.md",
  "tags": [],
  "version": "current",
  "frontMatter": {},
  "sidebar": "tutorialSidebar",
  "previous": {
    "title": "survey-vars",
    "permalink": "/user-guide/task-templates/survey-vars"
  },
  "next": {
    "title": "Schedules",
    "permalink": "/user-guide/schedules"
  }
}